<?xml version="1.0" encoding="UTF-8"?>
<objects serializationModel="Studio.02.01.00">
	<object class="ParameterPreset" id="{071ddab4-f2a9-4d4c-a49c-99ed065ed161}">
		<property name="name">
			<value>Mom</value>
		</property>
		<relationship name="folder">
			<destination>{bbf18c1f-8cbf-44ee-aaeb-4cee1e6e7e9b}</destination>
		</relationship>
		<relationship name="parameter">
			<destination>{e21bcbde-7d1c-426c-8f91-0d35dff3c016}</destination>
		</relationship>
	</object>
	<object class="GameParameter" id="{e21bcbde-7d1c-426c-8f91-0d35dff3c016}">
		<property name="initialValue">
			<value>0</value>
		</property>
	</object>
</objects>
